{"version": 0.6, "generator": "Overpass API 0.7.62.8 e802775f", "osm3s": {"timestamp_osm_base": "2025-10-11T00:46:26Z", "copyright": "The data included in this document is from www.openstreetmap.org. The data is made available under ODbL."}, "elements": [{"type": "node", "id": 104080353, "lat": 40.551776, "lon": -79.082855}, {"type": "node", "id": 104095959, "lat": 40.55273, "lon": -79.083952}, {"type": "node", "id": 104096010, "lat": 40.55155, "lon": -79.08258}, {"type": "node", "id": 104210590, "lat": 40.551302, "lon": -79.082263}, {"type": "node", "id": 104211863, "lat": 40.558498, "lon": -79.09807}, {"type": "node", "id": 104379333, "lat": 40.553868, "lon": -79.084973}, {"type": "node", "id": 104476025, "lat": 40.549973, "lon": -79.079211}, {"type": "node", "id": 104689497, "lat": 40.5580288, "lon": -79.1165284}, {"type": "node", "id": 104786081, "lat": 40.550271, "lon": -79.074542}, {"type": "node", "id": 104868980, "lat": 40.5581104, "lon": -79.1146355}, {"type": "node", "id": 104868989, "lat": 40.5582398, "lon": -79.1142646}, {"type": "node", "id": 104869000, "lat": 40.55945, "lon": -79.111102}, {"type": "node", "id": 104869015, "lat": 40.559638, "lon": -79.110561}, {"type": "node", "id": 104869029, "lat": 40.559653, "lon": -79.110462}, {"type": "node", "id": 104869042, "lat": 40.559723, "lon": -79.11}, {"type": "node", "id": 104869047, "lat": 40.559722, "lon": -79.109564}, {"type": "node", "id": 104869062, "lat": 40.559559, "lon": -79.108829}, {"type": "node", "id": 104869075, "lat": 40.559401, "lon": -79.107929}, {"type": "node", "id": 104869091, "lat": 40.55933, "lon": -79.107429}, {"type": "node", "id": 104869106, "lat": 40.559293, "lon": -79.106867}, {"type": "node", "id": 104869119, "lat": 40.559387, "lon": -79.105981}, {"type": "node", "id": 104869135, "lat": 40.559602, "lon": -79.105301}, {"type": "node", "id": 104869147, "lat": 40.560095, "lon": -79.104037}, {"type": "node", "id": 104869158, "lat": 40.560786, "lon": -79.102168}, {"type": "node", "id": 104869171, "lat": 40.56083, "lon": -79.101838}, {"type": "node", "id": 104869176, "lat": 40.560812, "lon": -79.101468}, {"type": "node", "id": 104869183, "lat": 40.560642, "lon": -79.100692}, {"type": "node", "id": 104869189, "lat": 40.560246, "lon": -79.099084}, {"type": "node", "id": 104869203, "lat": 40.560116, "lon": -79.098808}, {"type": "node", "id": 104869219, "lat": 40.559887, "lon": -79.098609}, {"type": "node", "id": 104869228, "lat": 40.559277, "lon": -79.09847}, {"type": "node", "id": 104869242, "lat": 40.558746, "lon": -79.098255}, {"type": "node", "id": 104869348, "lat": 40.558365, "lon": -79.09797}, {"type": "node", "id": 104869355, "lat": 40.558169, "lon": -79.097779}, {"type": "node", "id": 104869369, "lat": 40.558021, "lon": -79.097634}, {"type": "node", "id": 104869383, "lat": 40.557682, "lon": -79.097233}, {"type": "node", "id": 104869394, "lat": 40.55748, "lon": -79.096745}, {"type": "node", "id": 104869406, "lat": 40.557465, "lon": -79.096228}, {"type": "node", "id": 104869488, "lat": 40.557535, "lon": -79.095132}, {"type": "node", "id": 104869500, "lat": 40.557598, "lon": -79.094415}, {"type": "node", "id": 104869514, "lat": 40.55758, "lon": -79.093676}, {"type": "node", "id": 104869590, "lat": 40.557423, "lon": -79.093269}, {"type": "node", "id": 104869596, "lat": 40.557022, "lon": -79.092533}, {"type": "node", "id": 104869603, "lat": 40.556389, "lon": -79.089509}, {"type": "node", "id": 104869616, "lat": 40.55614, "lon": -79.088875}, {"type": "node", "id": 104869627, "lat": 40.555814, "lon": -79.088111}, {"type": "node", "id": 104869632, "lat": 40.555656, "lon": -79.087664}, {"type": "node", "id": 104869648, "lat": 40.555321, "lon": -79.086374}, {"type": "node", "id": 104869657, "lat": 40.555196, "lon": -79.086033}, {"type": "node", "id": 104869662, "lat": 40.554991, "lon": -79.085767}, {"type": "node", "id": 104869674, "lat": 40.553449, "lon": -79.084677}, {"type": "node", "id": 104869688, "lat": 40.553151, "lon": -79.084431}, {"type": "node", "id": 104869699, "lat": 40.551924, "lon": -79.083035}, {"type": "node", "id": 104869792, "lat": 40.551316, "lon": -79.082296}, {"type": "node", "id": 104869801, "lat": 40.551133, "lon": -79.081874}, {"type": "node", "id": 104869811, "lat": 40.5509, "lon": -79.081075}, {"type": "node", "id": 104869823, "lat": 40.550762, "lon": -79.08066}, {"type": "node", "id": 104869830, "lat": 40.550427, "lon": -79.080127}, {"type": "node", "id": 104869841, "lat": 40.550105, "lon": -79.079585}, {"type": "node", "id": 104869851, "lat": 40.549901, "lon": -79.078671}, {"type": "node", "id": 104869861, "lat": 40.549904, "lon": -79.077765}, {"type": "node", "id": 104869873, "lat": 40.549911, "lon": -79.075859}, {"type": "node", "id": 104869887, "lat": 40.549945, "lon": -79.075661}, {"type": "node", "id": 104869899, "lat": 40.551059, "lon": -79.07179}, {"type": "node", "id": 108815767, "lat": 40.8566459, "lon": -79.3225506}, {"type": "node", "id": 109153612, "lat": 40.8789733, "lon": -79.334361}, {"type": "node", "id": 109239012, "lat": 40.8711362, "lon": -79.3241121}, {"type": "node", "id": 109240136, "lat": 40.8572817, "lon": -79.3224352, "tags": {"railway": "level_crossing"}}, {"type": "node", "id": 109240139, "lat": 40.8577631, "lon": -79.3228}, {"type": "node", "id": 109240142, "lat": 40.858791, "lon": -79.323438}, {"type": "node", "id": 109240148, "lat": 40.859523, "lon": -79.32383}, {"type": "node", "id": 109240158, "lat": 40.861696, "lon": -79.324373}, {"type": "node", "id": 109240165, "lat": 40.863526, "lon": -79.324373}, {"type": "node", "id": 109240173, "lat": 40.864899, "lon": -79.324011}, {"type": "node", "id": 109240178, "lat": 40.866455, "lon": -79.324162}, {"type": "node", "id": 109240181, "lat": 40.866604, "lon": -79.324191}, {"type": "node", "id": 109240184, "lat": 40.867827, "lon": -79.324434}, {"type": "node", "id": 109240190, "lat": 40.869474, "lon": -79.324042}, {"type": "node", "id": 109240195, "lat": 40.87, "lon": -79.323861}, {"type": "node", "id": 109240202, "lat": 40.8708418, "lon": -79.3238512}, {"type": "node", "id": 109240208, "lat": 40.872631, "lon": -79.326393}, {"type": "node", "id": 109240213, "lat": 40.872905, "lon": -79.326604}, {"type": "node", "id": 109240223, "lat": 40.873683, "lon": -79.326755}, {"type": "node", "id": 109240230, "lat": 40.874278, "lon": -79.326484}, {"type": "node", "id": 109240237, "lat": 40.8750744, "lon": -79.3263901}, {"type": "node", "id": 109240243, "lat": 40.8762426, "lon": -79.3269582}, {"type": "node", "id": 109240249, "lat": 40.8781875, "lon": -79.3287101}, {"type": "node", "id": 109240259, "lat": 40.8784159, "lon": -79.3294076}, {"type": "node", "id": 109240264, "lat": 40.8788072, "lon": -79.3312524}, {"type": "node", "id": 109240272, "lat": 40.8788278, "lon": -79.3341066}, {"type": "node", "id": 5614454473, "lat": 40.8771318, "lon": -79.3275485}, {"type": "node", "id": 8333670361, "lat": 40.5539762, "lon": -79.0850495}, {"type": "node", "id": 12756601439, "lat": 40.5580504, "lon": -79.1148633}, {"type": "node", "id": 12756601440, "lat": 40.5580184, "lon": -79.1150454}, {"type": "node", "id": 12756601441, "lat": 40.5580043, "lon": -79.1152564}, {"type": "node", "id": 12756601442, "lat": 40.5580164, "lon": -79.1154595}, {"type": "node", "id": 12756601443, "lat": 40.5580404, "lon": -79.1156626}, {"type": "node", "id": 12756601444, "lat": 40.5580945, "lon": -79.1158737}, {"type": "node", "id": 12756601445, "lat": 40.5581246, "lon": -79.1160056}, {"type": "node", "id": 12756601446, "lat": 40.5581466, "lon": -79.1161055}, {"type": "node", "id": 12756601447, "lat": 40.5581466, "lon": -79.1161955}, {"type": "node", "id": 12756601448, "lat": 40.5581386, "lon": -79.1162984}, {"type": "node", "id": 12756601449, "lat": 40.5581186, "lon": -79.1163775}, {"type": "node", "id": 12756601450, "lat": 40.5580765, "lon": -79.116454, "tags": {"direction": "backward", "highway": "stop", "source": "Bing Streetside 2015"}}, {"type": "way", "id": 11714605, "nodes": [104689497, 12756601450, 12756601449, 12756601448, 12756601447, 12756601446, 12756601445, 12756601444, 12756601443, 12756601442, 12756601441, 12756601440, 12756601439, 104868980, 104868989, 104869000, 104869015, 104869029, 104869042, 104869047, 104869062, 104869075, 104869091, 104869106, 104869119, 104869135, 104869147, 104869158, 104869171, 104869176, 104869183, 104869189, 104869203, 104869219, 104869228, 104869242, 104211863, 104869348, 104869355, 104869369, 104869383, 104869394, 104869406, 104869488, 104869500, 104869514, 104869590, 104869596, 104869603, 104869616, 104869627, 104869632, 104869648, 104869657, 104869662, 8333670361, 104379333, 104869674, 104869688, 104095959, 104869699, 104080353, 104096010, 104869792, 104210590, 104869801, 104869811, 104869823, 104869830, 104869841, 104476025, 104869851, 104869861, 104869873, 104869887, 104786081, 104869899], "tags": {"highway": "unclassified", "name": "Snyder Road", "ref": "T760", "surface": "asphalt", "tiger:cfcc": "A41", "tiger:reviewed": "no", "tiger:zip_left": "15701", "tiger:zip_right": "15701"}}, {"type": "way", "id": 12075161, "nodes": [108815767, 109240136, 109240139, 109240142, 109240148, 109240158, 109240165, 109240173, 109240178, 109240181, 109240184, 109240190, 109240195, 109240202, 109239012, 109240208, 109240213, 109240223, 109240230, 109240237, 109240243, 5614454473, 109240249, 109240259, 109240264, 109240272, 109153612], "tags": {"highway": "unclassified", "lanes": "1", "maxspeed": "25 mph", "name": "T776 - Harris Road", "ref": "T776", "surface": "dirt", "tiger:cfcc": "A41", "tiger:reviewed": "no"}}]}